collective.formsupport.counter-1.0.3-py3.10-nspkg.pth
collective/formsupport/counter/__init__.py
collective/formsupport/counter/config.py
collective/formsupport/counter/configure.zcml
collective/formsupport/counter/interfaces.py
collective/formsupport/counter/permissions.zcml
collective/formsupport/counter/setuphandlers.py
collective/formsupport/counter/testing.py
collective/formsupport/counter/adapters/__init__.py
collective/formsupport/counter/adapters/configure.zcml
collective/formsupport/counter/adapters/data.py
collective/formsupport/counter/adapters/post.py
collective/formsupport/counter/browser/__init__.py
collective/formsupport/counter/browser/configure.zcml
collective/formsupport/counter/browser/overrides/.gitkeep
collective/formsupport/counter/browser/static/.gitkeep
collective/formsupport/counter/datamanager/__init__.py
collective/formsupport/counter/datamanager/configure.zcml
collective/formsupport/counter/events/__init__.py
collective/formsupport/counter/events/configure.zcml
collective/formsupport/counter/locales/README.rst
collective/formsupport/counter/locales/__init__.py
collective/formsupport/counter/locales/collective.formsupport.counter.pot
collective/formsupport/counter/locales/update.py
collective/formsupport/counter/locales/update.sh
collective/formsupport/counter/locales/en/LC_MESSAGES/collective.formsupport.counter.mo
collective/formsupport/counter/locales/en/LC_MESSAGES/collective.formsupport.counter.po
collective/formsupport/counter/locales/it/LC_MESSAGES/collective.formsupport.counter.mo
collective/formsupport/counter/locales/it/LC_MESSAGES/collective.formsupport.counter.po
collective/formsupport/counter/profiles/default/browserlayer.xml
collective/formsupport/counter/profiles/default/catalog.xml
collective/formsupport/counter/profiles/default/metadata.xml
collective/formsupport/counter/profiles/default/rolemap.xml
collective/formsupport/counter/profiles/default/registry/main.xml
collective.formsupport.counter-1.0.3.dist-info/LICENSE.GPL
collective.formsupport.counter-1.0.3.dist-info/LICENSE.rst
collective.formsupport.counter-1.0.3.dist-info/METADATA
collective.formsupport.counter-1.0.3.dist-info/WHEEL
collective.formsupport.counter-1.0.3.dist-info/entry_points.txt
collective.formsupport.counter-1.0.3.dist-info/namespace_packages.txt
collective.formsupport.counter-1.0.3.dist-info/top_level.txt
collective.formsupport.counter-1.0.3.dist-info/RECORD
